Metadata-Version: 2.1
Name: framemagic
Version: 0.1.1
Summary: Python magic based on frame stack call
Home-page: https://github.com/sammnnz/PyMagic
Author: Sam Nazarov
Author-email: drozdosam@mail.ru
License: MIT
Keywords: frame,getframe,nameof,stackframe
Platform: any
Classifier: Programming Language :: Python :: 3
Classifier: Programming Language :: Python :: 3 :: Only
Classifier: Programming Language :: Python :: 3.5
Classifier: Programming Language :: Python :: 3.6
Classifier: Programming Language :: Python :: 3.7
Classifier: Programming Language :: Python :: 3.8
Classifier: Programming Language :: Python :: 3.9
Requires-Python: >=3.5
Provides-Extra: testing
License-File: LICENSE
